moji/__init__.py
moji/moji.py
mojii-0.1.3.dist-info/METADATA
mojii-0.1.3.dist-info/WHEEL
mojii-0.1.3.dist-info/top_level.txt
mojii-0.1.3.dist-info/RECORD
